sandboxai/__init__.py
sandboxai/embedded.py
sandboxai/sandbox.py
sandboxai/sandbox_test.py
sandboxai/api/__init__.py
sandboxai/api/v1.py
sandboxai/client/v1.py
sandboxai/experimental/crewai.py
sandboxai/test/e2e/test_client_v1.py
sandboxai_client-0.0.2.dist-info/METADATA
sandboxai_client-0.0.2.dist-info/WHEEL
sandboxai_client-0.0.2.dist-info/top_level.txt
sandboxai_client-0.0.2.dist-info/RECORD
