Metadata-Version: 2.2
Name: sandboxai-client
Version: 0.0.2
Summary: Secure sandboxes for AI agents and LLMs.
Project-URL: Homepage, https://github.com/substratusai/sandboxai
Project-URL: Repository, https://github.com/substratusai/sandboxai.git
Project-URL: Documentation, https://github.com/substratusai/sandboxai
Requires-Python: >=3.10
Requires-Dist: pydantic
Requires-Dist: requests
Provides-Extra: examples
Requires-Dist: swarm; extra == "examples"
